finter/__init__.py
finter/api_client.py
finter/cli.py
finter/configuration.py
finter/log.py
finter/rest.py
finter/settings.py
finter/ai/__init__.py
finter/ai/gpt/__init__.py
finter/ai/gpt/cm_docs.py
finter/ai/gpt/config.py
finter/ai/gpt/cookbook.py
finter/ai/gpt/log_tag.py
finter/ai/gpt/release_note.py
finter/ai/gpt/summary_strategy.py
finter/ai/quanda_bot/__init__.py
finter/ai/quanda_bot/generate.py
finter/api/__init__.py
finter/api/alpha_api.py
finter/api/aws_credentials_api.py
finter/api/calendar_api.py
finter/api/content_api.py
finter/api/default_api.py
finter/api/flexible_fund_api.py
finter/api/fund_api.py
finter/api/gcs_credentials_api.py
finter/api/mapper_api.py
finter/api/metafund_api.py
finter/api/performance_api.py
finter/api/portfolio_api.py
finter/api/production_api.py
finter/api/quanda_bot_api.py
finter/api/quanda_data_api.py
finter/api/quanda_db_api.py
finter/api/quanda_flow_api.py
finter/api/simulation_api.py
finter/api/sm_api.py
finter/api/submission_api.py
finter/api/symbol_api.py
finter/api/universe_api.py
finter/api/user_api.py
finter/backtest/__init__.py
finter/backtest/intraday_simulator.py
finter/backtest/parameter_analyzer.py
finter/backtest/simulator.py
finter/backtest/__legacy_core/__init__.py
finter/backtest/__legacy_core/core.py
finter/backtest/__legacy_support/__init__.py
finter/backtest/__legacy_support/main.py
finter/backtest/base/__init__.py
finter/backtest/base/main.py
finter/backtest/base/variables.py
finter/backtest/builder/__init__.py
finter/backtest/builder/main.py
finter/backtest/builder/processor.py
finter/backtest/builder/volume_limit_processors.py
finter/backtest/config/__init__.py
finter/backtest/config/config.py
finter/backtest/config/frequency.py
finter/backtest/config/simulator.py
finter/backtest/config/templates.py
finter/backtest/core/__init__.py
finter/backtest/core/constraint.py
finter/backtest/core/execution.py
finter/backtest/core/intermediary.py
finter/backtest/core/pnl.py
finter/backtest/core/target.py
finter-0.5.39.dist-info/METADATA
finter-0.5.39.dist-info/WHEEL
finter-0.5.39.dist-info/entry_points.txt
finter-0.5.39.dist-info/top_level.txt
finter-0.5.39.dist-info/RECORD
