Metadata-Version: 2.1
Name: finter
Version: 0.5.39
Summary: FINTER API
Home-page: https://quantit.gitbook.io/finter/
Author: Quantit <finter_support@quantit.io>
Author-email: 
Keywords: Swagger,FINTER API
Requires-Python: <3.14,>=3.11
Requires-Dist: urllib3>=1.15
Requires-Dist: six>=1.10
Requires-Dist: pyarrow<20.0.0,>=0.17.0
Requires-Dist: s3fs
Requires-Dist: certifi
Requires-Dist: python-dateutil
Requires-Dist: nbformat
Requires-Dist: nbconvert
Requires-Dist: python-dotenv
Requires-Dist: requests
Requires-Dist: halo
Requires-Dist: ipywidgets
Requires-Dist: pydantic>=1.9.0
Requires-Dist: pyyaml
Requires-Dist: cachetools
Requires-Dist: boto3
Requires-Dist: click
Requires-Dist: blosc>=1.10.6
Requires-Dist: typing-extensions
Requires-Dist: pandas
Requires-Dist: numpy
Requires-Dist: scipy
Requires-Dist: qore-client
Requires-Dist: awswrangler
Requires-Dist: tqdm
Requires-Dist: numba
Requires-Dist: matplotlib
Requires-Dist: sidecar
Requires-Dist: polars
Requires-Dist: google-cloud-storage
Requires-Dist: google-auth
Requires-Dist: fastavro
